toshi_hazard_store/__init__.py
toshi_hazard_store/config.py
toshi_hazard_store/model/__init__.py
toshi_hazard_store/model/attributes/__init__.py
toshi_hazard_store/model/attributes/attributes.py
toshi_hazard_store/model/attributes/enum_attribute.py
toshi_hazard_store/model/attributes/enum_constrained_attribute.py
toshi_hazard_store/model/constraints.py
toshi_hazard_store/model/gridded_hazard.py
toshi_hazard_store/model/hazard_models_manager.py
toshi_hazard_store/model/hazard_models_pydantic.py
toshi_hazard_store/model/pyarrow/dataset_schema.py
toshi_hazard_store/model/pyarrow/pyarrow_aggr_dataset.py
toshi_hazard_store/model/pyarrow/pyarrow_dataset.py
toshi_hazard_store/model/revision_4/__init__.py
toshi_hazard_store/model/revision_4/extract_classical_hdf5.py
toshi_hazard_store/model/revision_4/extract_disagg.py
toshi_hazard_store/model/revision_4/extract_disagg_hdf5.py
toshi_hazard_store/oq_import/__init__.py
toshi_hazard_store/oq_import/aws_ecr_docker_image.py
toshi_hazard_store/oq_import/oq_config.py
toshi_hazard_store/oq_import/oq_manipulate_hdf5.py
toshi_hazard_store/oq_import/parse_oq_realizations.py
toshi_hazard_store/oq_import/toshi_api_client.py
toshi_hazard_store/oq_import/toshi_api_subtask.py
toshi_hazard_store/oq_import/transform.py
toshi_hazard_store/pynamodb_settings.py
toshi_hazard_store/query/__init__.py
toshi_hazard_store/query/datasets.py
toshi_hazard_store/query/gridded_hazard_query.py
toshi_hazard_store/query/hazard_query.py
toshi_hazard_store/resources/metadata/compatible_hazard_calculations/NZSHM22.json
toshi_hazard_store/resources/metadata/hazard_curve_producer_configs/7ba0a25c8c11a5406c93736dc971e32a86859cc736309e8cba21cfcb153fa1dd.json
toshi_hazard_store/resources/metadata/hazard_curve_producer_configs/8c09bffb9f4cf88bbcc96876b029aa91a638620810d2c0917dfba53454e21ac2.json
toshi_hazard_store/resources/metadata/hazard_curve_producer_configs/e8b44b806570dcdc4a725cafc2fbaf6dae99dbfbe69345d86b3069d3fe4a2bc6.json
toshi_hazard_store-1.3.1.dist-info/METADATA
toshi_hazard_store-1.3.1.dist-info/WHEEL
toshi_hazard_store-1.3.1.dist-info/entry_points.txt
toshi_hazard_store-1.3.1.dist-info/licenses/LICENSE
toshi_hazard_store-1.3.1.dist-info/RECORD
