Metadata-Version: 2.4
Name: toshi-hazard-store
Version: 1.3.1
Summary: Library for saving and retrieving NZHSM openquake hazard results with convenience (uses AWS Dynamodb).
License-Expression: AGPL-3.0-or-later
License-File: LICENSE
Author: Chris B Chamberlain
Author-email: chrisbc@artisan.co.nz
Requires-Python: >=3.10,<4.0
Classifier: Development Status :: 2 - Pre-Alpha
Classifier: Intended Audience :: Developers
Classifier: Natural Language :: English
Classifier: Programming Language :: Python :: 3
Classifier: Programming Language :: Python :: 3.10
Classifier: Programming Language :: Python :: 3.11
Classifier: Programming Language :: Python :: 3.12
Requires-Dist: nshm-toshi-client (>=1.0.1)
Requires-Dist: numpy (>=1.24)
Requires-Dist: nzshm-common (>=0.8.4)
Requires-Dist: nzshm-model (>=0.13.6)
Requires-Dist: pandas (>=2)
Requires-Dist: pyarrow (>=20.0.0)
Requires-Dist: pydantic (>=2.11.5)
Requires-Dist: pynamodb (>=6.0.0)
Requires-Dist: pynamodb-attributes (>=0.4.0)
Requires-Dist: python-dotenv (>=1.0.1)
Requires-Dist: s3path (>=0.6.1)
